judgeval/__init__.py
judgeval/clients.py
judgeval/constants.py
judgeval/evaluation_run.py
judgeval/judgment_client.py
judgeval/rules.py
judgeval/run_evaluation.py
judgeval/version_check.py
judgeval/common/__init__.py
judgeval/common/exceptions.py
judgeval/common/logger.py
judgeval/common/utils.py
judgeval/common/api/__init__.py
judgeval/common/api/api.py
judgeval/common/api/constants.py
judgeval/common/storage/__init__.py
judgeval/common/storage/s3_storage.py
judgeval/common/tracer/__init__.py
judgeval/common/tracer/constants.py
judgeval/common/tracer/core.py
judgeval/common/tracer/otel_exporter.py
judgeval/common/tracer/otel_span_processor.py
judgeval/common/tracer/span_processor.py
judgeval/common/tracer/span_transformer.py
judgeval/common/tracer/trace_manager.py
judgeval/data/__init__.py
judgeval/data/example.py
judgeval/data/judgment_types.py
judgeval/data/result.py
judgeval/data/scorer_data.py
judgeval/data/tool.py
judgeval/data/trace.py
judgeval/data/trace_run.py
judgeval/data/datasets/__init__.py
judgeval/data/datasets/dataset.py
judgeval/data/datasets/eval_dataset_client.py
judgeval/data/scripts/fix_default_factory.py
judgeval/data/scripts/openapi_transform.py
judgeval/examples/generate_and_run_scorer.py
judgeval/examples/langgraph_basic.py
judgeval/integrations/langgraph.py
judgeval/judges/__init__.py
judgeval/judges/base_judge.py
judgeval/judges/litellm_judge.py
judgeval/judges/mixture_of_judges.py
judgeval/judges/together_judge.py
judgeval/judges/utils.py
judgeval/scorers/__init__.py
judgeval/scorers/agent_scorer.py
judgeval/scorers/api_scorer.py
judgeval/scorers/base_scorer.py
judgeval/scorers/example_scorer.py
judgeval/scorers/exceptions.py
judgeval/scorers/score.py
judgeval/scorers/scorer_codegen.py
judgeval/scorers/trajectory_scorer.py
judgeval/scorers/utils.py
judgeval/scorers/judgeval_scorers/__init__.py
judgeval/scorers/judgeval_scorers/api_scorers/__init__.py
judgeval/scorers/judgeval_scorers/api_scorers/answer_correctness.py
trajectoryeval-0.0.2.dist-info/METADATA
trajectoryeval-0.0.2.dist-info/WHEEL
trajectoryeval-0.0.2.dist-info/licenses/LICENSE.md
trajectoryeval-0.0.2.dist-info/RECORD
